baseqSNV/__init__.py
baseqSNV/annovar.py
baseqSNV/cmd.py
baseqSNV/config.py
baseqSNV/pipe.py
baseqSNV/process.py
baseqSNV/quality.py
baseqSNV/gatk/__init__.py
baseqSNV/gatk/align.py
baseqSNV/gatk/bqsr.py
baseqSNV/gatk/callvar.py
baseqSNV/gatk/createpon.py
baseqSNV/gatk/markdup.py
baseqSNV/gatk/mutect.py
baseqSNV/gatk/pipe.py
baseqSNV/gatk/selectvar.py
baseqSNV/qc/__init__.py
baseqSNV/qc/cmd.py
baseqSNV/qc/enrich.py
baseqSNV/qc/saturate.py
baseqSNV/vcf/GATK.py
baseqSNV/vcf/__init__.py
baseqSNV/vcf/annovar.py
baseqSNV/vcf/cmd.py
baseqSNV-1.6.dist-info/DESCRIPTION.rst
baseqSNV-1.6.dist-info/METADATA
baseqSNV-1.6.dist-info/RECORD
baseqSNV-1.6.dist-info/WHEEL
baseqSNV-1.6.dist-info/entry_points.txt
baseqSNV-1.6.dist-info/metadata.json
baseqSNV-1.6.dist-info/top_level.txt
